antx/__init__.py
antx/ann_patterns.py
antx/core.py
antx/utils.py
antx-0.1.11.dist-info/LICENSE
antx-0.1.11.dist-info/METADATA
antx-0.1.11.dist-info/WHEEL
antx-0.1.11.dist-info/top_level.txt
antx-0.1.11.dist-info/RECORD
